oopyconnector
