Metadata-Version: 1.1
Name: oopyconnector
Version: 0.78.41
Summary: Python wrapper for the Only Once API
Home-page: http://github.com/wizardofzos/onlyonce-python
Author: Henri Kuiper
Author-email: henrikuiper@zdevops.com
License: BSD
Platform: UNKNOWN
Classifier: Development Status :: 4 - Beta
Classifier: Intended Audience :: Developers
Classifier: License :: OSI Approved :: BSD License
Classifier: Programming Language :: Python :: 2
Classifier: Programming Language :: Python :: 2.6
Classifier: Programming Language :: Python :: 2.7
Classifier: Programming Language :: Python :: 3
Classifier: Programming Language :: Python :: 3.3
Classifier: Programming Language :: Python :: 3.4
Classifier: Programming Language :: Python :: 3.5
